[{"bullet":{"color":"RED"},"cardType":"GUNSIGHT"}, {"bullet":{"color":"RED"},"cardType":"KINETICRAY"}, {"bullet":{"color":"RED"},"cardType":"TELEPORTER"}, {"bullet":{"color":"RED"},"cardType":"VENOMGRENADE"}, {"bullet":{"color":"YELLOW"},"cardType":"GUNSIGHT"}, {"bullet":{"color":"YELLOW"},"cardType":"KINETICRAY"}, {"bullet":{"color":"YELLOW"},"cardType":"TELEPORTER"}, {"bullet":{"color":"YELLOW"},"cardType":"VENOMGRENADE"}, {"bullet":{"color":"BLUE"},"cardType":"GUNSIGHT"}, {"bullet":{"color":"BLUE"},"cardType":"KINETICRAY"}, {"bullet":{"color":"BLUE"},"cardType":"TELEPORTER"}, {"bullet":{"color":"BLUE"},"cardType":"VENOMGRENADE"}]
